LICENSE
README.md
setup.cfg
setup.py
celebrity_births/__init__.py
celebrity_births/__main__.py
celebrity_births/date.py
celebrity_births/example.py
celebrity_births/scraper.py
celebrity_births_test_ossama.egg-info/PKG-INFO
celebrity_births_test_ossama.egg-info/SOURCES.txt
celebrity_births_test_ossama.egg-info/dependency_links.txt
celebrity_births_test_ossama.egg-info/requires.txt
celebrity_births_test_ossama.egg-info/top_level.txt
scripts/hello